text2digits/__init__.py
text2digits/rules.py
text2digits/text2digits.py
text2digits/text_processing_helpers.py
text2digits/tokens_basic.py
text2digits/tokens_rules.py
text2digits_custom-0.0.9.dist-info/LICENSE
text2digits_custom-0.0.9.dist-info/METADATA
text2digits_custom-0.0.9.dist-info/WHEEL
text2digits_custom-0.0.9.dist-info/top_level.txt
text2digits_custom-0.0.9.dist-info/RECORD
