Metadata-Version: 2.1
Name: text2digits-custom
Version: 0.0.9
Summary: A small library to convert text numbers to digits in a string; customized
Home-page: https://github.com/ManeshNarayan/text2digits_custom
Author: Shail Choksi, Manesh Narayan
Author-email: kmaneshnarayan@gmail.com
License: UNKNOWN
Project-URL: Source, https://github.com/careless25/text2digits
Keywords: text2numbers words2numbers digits numbers custom
Platform: UNKNOWN
Classifier: Programming Language :: Python :: 3
Classifier: License :: OSI Approved :: MIT License
Classifier: Operating System :: OS Independent
